{"tag":"career_planning","cities":[{"city":"Philadelphia","count":1,"med_date":"2010-08-05T00:00:00.000Z","releases":[{"url":"http://cityofphiladelphia.wordpress.com/https://cityofphiladelphia.wordpress.com/2010/08/05/mayor-nutter-congratulates-workready-philadelphia-interns/","city":"Philadelphia","hash":"http://cityofphiladelphia.wordpress.com/https://cityofphiladelphia.wordpress.com/2010/08/05/mayor-nutter-congratulates-workready-philadelphia-interns/:2010-08-05T00:00:00.000Z","date":"2010-08-05T00:00:00.000Z","title":"MAYOR NUTTER CONGRATULATES WORKREADY PHILADELPHIA INTERNS"}]}]}